light_curve_python-0.3.5.dist-info/METADATA
light_curve_python-0.3.5.dist-info/WHEEL
light_curve/__init__.py
light_curve/light_curve.cpython-38-x86_64-linux-gnu.so
light_curve_python-0.3.5.dist-info/RECORD
