Metadata-Version: 2.1
Name: light-curve-python
Version: 0.3.5
Classifier: Intended Audience :: Science/Research
Classifier: License :: OSI Approved :: MIT License
Classifier: Programming Language :: Python
Classifier: Programming Language :: Python :: 3 :: Only
Classifier: Programming Language :: Python :: 3.6
Classifier: Programming Language :: Python :: 3.7
Classifier: Programming Language :: Python :: 3.8
Classifier: Programming Language :: Python :: 3.9
Classifier: Programming Language :: Rust
Classifier: Topic :: Scientific/Engineering :: Astronomy
Requires-Dist: numpy
Summary: Feature extractor from noisy time series
Author: Konstantin Malanchev <hombit@gmail.com>, Anastasia Lavrukhina <lavrukhina.ad@gmail.com>
Author-email: Konstantin Malanchev <hombit@gmail.com>, Anastasia Lavrukhina <lavrukhina.ad@gmail.com>
License: GPL-3.0-or-later
Project-URL: Source Code, https://github.com/light-curve/light-curve
